github_issue_checkout.py
github_issue_checkout-0.2.1.dist-info/entry_points.txt
github_issue_checkout-0.2.1.dist-info/WHEEL
github_issue_checkout-0.2.1.dist-info/METADATA
github_issue_checkout-0.2.1.dist-info/RECORD
